getBCE/Main.py
getBCE/Reader.py
getBCE/Utils.py
getBCE/__init__.py
getBCE-1.5.4.dist-info/METADATA
getBCE-1.5.4.dist-info/WHEEL
getBCE-1.5.4.dist-info/top_level.txt
getBCE-1.5.4.dist-info/RECORD
