Metadata-Version: 2.1
Name: getBCE
Version: 1.5.4
Summary: Download data from BCE (Banco Central del ecuador) webpage
Home-page: https://github.com//Daniejar27/BCE
Download-URL: https://github.com//Daniejar27/BCE
Author: S. Daniel Jaramillo
Author-email: losteven2018@outlook.com
License: UNKNOWN
Keywords: Economics,Banco Central,BCE,economía
Platform: UNKNOWN
Requires-Python: >= 3.8
Requires-Dist: requests
Requires-Dist: bs4
Requires-Dist: urllib3
Provides-Extra: tests
Requires-Dist: pytest ; extra == 'tests'
